CHANGES.txt
LICENSE.txt
MANIFEST.in
README
requirements.txt
setup.py
Klout.egg-info/PKG-INFO
Klout.egg-info/SOURCES.txt
Klout.egg-info/dependency_links.txt
Klout.egg-info/top_level.txt
docs/_build/text/design-philosophy.txt
docs/_build/text/index.txt
klout/__init__.py
klout/_version.py
klout/api.py