Metadata-Version: 1.0
Name: Klout
Version: 0.1.3
Summary: Minimalist Klout API interface.
Home-page: http://pypi.python.org/pypi/klout/
Author: Irfan Ahmad
Author-email: klout@i.com.pk
License: LICENSE.txt
Platform: UNKNOWN
Classifier: Intended Audience :: Developers
Classifier: License :: OSI Approved :: MIT License
Classifier: Natural Language :: English
Classifier: Operating System :: OS Independent
Classifier: Programming Language :: Python
Classifier: Programming Language :: Python :: 2.5
Classifier: Programming Language :: Python :: 2.6
Classifier: Programming Language :: Python :: 2.7
Classifier: Programming Language :: Python :: 3
Classifier: Topic :: Communications
